rh_gitleaks/__init__.py
rh_gitleaks-0.0.0.dist-info/METADATA
rh_gitleaks-0.0.0.dist-info/WHEEL
rh_gitleaks-0.0.0.dist-info/RECORD
